{
  "RSpec": {
    "coverage": {
      "/Users/drewwilliams/turing/3module/projects/sweaterweather/app/models/application_record.rb": {
        "lines": [
          0,
          0,
          0
        ],
        "branches": {
        }
      },
      "/Users/drewwilliams/turing/3module/projects/sweaterweather/app/serializers/forecast_serializer.rb": {
        "lines": [
          0,
          0,
          0,
          0
        ],
        "branches": {
        }
      },
      "/Users/drewwilliams/turing/3module/projects/sweaterweather/app/facades/forecast_facade.rb": {
        "lines": [
          0,
          0,
          0,
          0,
          0,
          0,
          0,
          0,
          0
        ],
        "branches": {
        }
      },
      "/Users/drewwilliams/turing/3module/projects/sweaterweather/app/poros/forecast.rb": {
        "lines": [
          0,
          0,
          0,
          0,
          0,
          0,
          0,
          0,
          null,
          0,
          0,
          0,
          0,
          0,
          0,
          0,
          0,
          0,
          null,
          0,
          0,
          0,
          0,
          0,
          0,
          0,
          0,
          0,
          0,
          0,
          0,
          0,
          null,
          0,
          0,
          0,
          0,
          0,
          0,
          0,
          0,
          0,
          0,
          0,
          null,
          0,
          0,
          0,
          0,
          0,
          0
        ],
        "branches": {
        }
      },
      "/Users/drewwilliams/turing/3module/projects/sweaterweather/app/controllers/application_controller.rb": {
        "lines": [
          0,
          0
        ],
        "branches": {
        }
      },
      "/Users/drewwilliams/turing/3module/projects/sweaterweather/app/controllers/api/v1/forecast_controller.rb": {
        "lines": [
          0,
          0,
          0,
          0,
          0,
          0
        ],
        "branches": {
        }
      },
      "/Users/drewwilliams/turing/3module/projects/sweaterweather/app/services/map_service.rb": {
        "lines": [
          0,
          0,
          0,
          0,
          null,
          0,
          0,
          0,
          0,
          0,
          0,
          0,
          null,
          0,
          0,
          0,
          0
        ],
        "branches": {
        }
      },
      "/Users/drewwilliams/turing/3module/projects/sweaterweather/app/services/weather_service.rb": {
        "lines": [
          0,
          0,
          0,
          0,
          null,
          0,
          0,
          0,
          0,
          0,
          0,
          0,
          null,
          0,
          0,
          0,
          0
        ],
        "branches": {
        }
      }
    },
    "timestamp": 1604938578
  }
}
